sketulate/__init__.py
sketulate/functions.py
sketulate/interactions.py
sketulate-0.1.0.dist-info/METADATA
sketulate-0.1.0.dist-info/WHEEL
sketulate-0.1.0.dist-info/licenses/LICENSE
sketulate-0.1.0.dist-info/RECORD
