Metadata-Version: 2.4
Name: sketulate
Version: 0.1.0
Summary: Sketchable function and density simulations for data science
Project-URL: Homepage, https://github.com/aaron1rcl/sketulate
Project-URL: Issues, https://github.com/aaron1rcl/sketulate/issues
Author-email: Aaron <aaron_rcl@hotmail.com>
License: This is free and unencumbered software released into the public domain.
License-File: LICENSE
Classifier: License :: OSI Approved :: MIT License
Classifier: Operating System :: OS Independent
Classifier: Programming Language :: Python :: 3
Requires-Python: >=3.11
Requires-Dist: ipycanvas
Requires-Dist: ipywidgets
Requires-Dist: matplotlib
Requires-Dist: numpy==2.0.0
Requires-Dist: plotly
Requires-Dist: scikit-learn
Requires-Dist: scipy
